// class version 50.0 (50)
// access flags 0x20
class net/minecraft/client/gui/inventory/GuiBeacon$ConfirmButton extends net/minecraft/client/gui/inventory/GuiBeacon$Button  {

  // compiled from: GuiBeacon.java

  @Lcpw/mods/fml/relauncher/SideOnly;(value=Lcpw/mods/fml/relauncher/Side;.CLIENT)
  // access flags 0x0
  INNERCLASS net/minecraft/client/gui/inventory/GuiBeacon$ConfirmButton net/minecraft/client/gui/inventory/GuiBeacon ConfirmButton
  // access flags 0x8
  static INNERCLASS net/minecraft/client/gui/inventory/GuiBeacon$Button net/minecraft/client/gui/inventory/GuiBeacon Button

  // access flags 0x1A
  private final static Ljava/lang/String; __OBFID = "CL_00000741"

  // access flags 0x1010
  final synthetic Lnet/minecraft/client/gui/inventory/GuiBeacon; this$0

  // access flags 0x1
  public <init>(Lnet/minecraft/client/gui/inventory/GuiBeacon;III)V
   L0
    LINENUMBER 312 L0
    ALOAD 0
    ALOAD 1
    PUTFIELD net/minecraft/client/gui/inventory/GuiBeacon$ConfirmButton.this$0 : Lnet/minecraft/client/gui/inventory/GuiBeacon;
   L1
    LINENUMBER 313 L1
    ALOAD 0
    ILOAD 2
    ILOAD 3
    ILOAD 4
    INVOKESTATIC net/minecraft/client/gui/inventory/GuiBeacon.access$000 ()Lnet/minecraft/util/ResourceLocation;
    BIPUSH 90
    SIPUSH 220
    INVOKESPECIAL net/minecraft/client/gui/inventory/GuiBeacon$Button.<init> (IIILnet/minecraft/util/ResourceLocation;II)V
   L2
    LINENUMBER 314 L2
    RETURN
   L3
    LOCALVARIABLE this Lnet/minecraft/client/gui/inventory/GuiBeacon$ConfirmButton; L0 L3 0
    LOCALVARIABLE this$0 Lnet/minecraft/client/gui/inventory/GuiBeacon; L0 L3 1
    LOCALVARIABLE p_i1075_2_ I L0 L3 2
    LOCALVARIABLE p_i1075_3_ I L0 L3 3
    LOCALVARIABLE p_i1075_4_ I L0 L3 4
    MAXSTACK = 7
    MAXLOCALS = 5

  // access flags 0x1
  public func_146111_b(II)V
    ALOAD 0
    GETFIELD net/minecraft/client/gui/inventory/GuiBeacon$ConfirmButton.this$0 : Lnet/minecraft/client/gui/inventory/GuiBeacon;
    DUP
    GETFIELD net/minecraft/client/gui/inventory/GuiContainer.manager : Lcodechicken/nei/guihook/GuiContainerManager;
    SWAP
    DUP
    GETFIELD net/minecraft/client/gui/inventory/GuiContainer.guiLeft : I
    ILOAD 1
    IADD
    SWAP
    GETFIELD net/minecraft/client/gui/inventory/GuiContainer.guiTop : I
    ILOAD 2
    IADD
    INVOKEVIRTUAL codechicken/nei/guihook/GuiContainerManager.objectUnderMouse (II)Z
    IFEQ L0
    RETURN
   L0
    LINENUMBER 318 L0
   FRAME FULL [net/minecraft/client/gui/inventory/GuiBeacon$ConfirmButton I I] []
    ALOAD 0
    GETFIELD net/minecraft/client/gui/inventory/GuiBeacon$ConfirmButton.this$0 : Lnet/minecraft/client/gui/inventory/GuiBeacon;
    LDC "gui.done"
    ICONST_0
    ANEWARRAY java/lang/Object
    INVOKESTATIC net/minecraft/client/resources/I18n.format (Ljava/lang/String;[Ljava/lang/Object;)Ljava/lang/String;
    ILOAD 1
    ILOAD 2
    INVOKESTATIC net/minecraft/client/gui/inventory/GuiBeacon.access$200 (Lnet/minecraft/client/gui/inventory/GuiBeacon;Ljava/lang/String;II)V
   L1
    LINENUMBER 319 L1
    RETURN
   L2
    LOCALVARIABLE this Lnet/minecraft/client/gui/inventory/GuiBeacon$ConfirmButton; L0 L2 0
    LOCALVARIABLE p_146111_1_ I L0 L2 1
    LOCALVARIABLE p_146111_2_ I L0 L2 2
    MAXSTACK = 4
    MAXLOCALS = 3
}
